MANIFEST.in
README.txt
setup.py
buildout/README.txt
buildout/bootstrap.py
buildout/buildout.cfg
buildout/plone4-0-1.cfg
buildout/products/README.txt
buildout/src/README.txt
buildout/var/README.txt
collective/__init__.py
collective.examples.diazo.egg-info/PKG-INFO
collective.examples.diazo.egg-info/SOURCES.txt
collective.examples.diazo.egg-info/dependency_links.txt
collective.examples.diazo.egg-info/entry_points.txt
collective.examples.diazo.egg-info/namespace_packages.txt
collective.examples.diazo.egg-info/not-zip-safe
collective.examples.diazo.egg-info/paster_plugins.txt
collective.examples.diazo.egg-info/requires.txt
collective.examples.diazo.egg-info/top_level.txt
collective/examples/__init__.py
collective/examples/diazo/__init__.py
collective/examples/diazo/configure.zcml
collective/examples/diazo/tests.py
collective/examples/diazo/version.txt
collective/examples/diazo/profiles/default/examples.diazo_various.txt
collective/examples/diazo/profiles/default/metadata.xml
collective/examples/diazo/profiles/default/registry.xml
collective/examples/diazo/static/collective-xdv-example/rules-document.xml
collective/examples/diazo/static/collective-xdv-example/rules-standard.xml
collective/examples/diazo/static/collective-xdv-example/rules.xml
collective/examples/diazo/static/collective-xdv-example/theme-news.html
collective/examples/diazo/static/collective-xdv-example/theme.html
collective/examples/diazo/static/orange_sunset/contact.html
collective/examples/diazo/static/orange_sunset/index.html
collective/examples/diazo/static/orange_sunset/page1.html
collective/examples/diazo/static/orange_sunset/page2.html
collective/examples/diazo/static/orange_sunset/page3.html
collective/examples/diazo/static/orange_sunset/rules.xml
collective/examples/diazo/static/orange_sunset/style/back.png
collective/examples/diazo/static/orange_sunset/style/colour.css
collective/examples/diazo/static/orange_sunset/style/graphic.jpg
collective/examples/diazo/static/orange_sunset/style/link.png
collective/examples/diazo/static/orange_sunset/style/logo.jpg
collective/examples/diazo/static/orange_sunset/style/menu.png
collective/examples/diazo/static/orange_sunset/style/menu_hover.png
collective/examples/diazo/static/orange_sunset/style/sbi_header.png
collective/examples/diazo/static/orange_sunset/style/style.css
docs/C-X-EXAMPLE.txt
docs/HISTORY.txt
docs/INSTALL.txt
docs/LICENSE.GPL
docs/LICENSE.txt
docs/ORANGE-SUNSET-THEME.txt
docs/TODO.txt