Metadata-Version: 1.0
Name: collective.examples.diazo
Version: 0.2
Summary: Example of Diazo (xdv) usage in Plone
Home-page: http://svn.plone.org/svn/collective/
Author: UNKNOWN
Author-email: UNKNOWN
License: GPL
Platform: UNKNOWN
Classifier: Framework :: Plone
Classifier: Programming Language :: Python
